Taowa_win/__init__.py
Taowa_win/taowa_win32.py
Taowa_win/按键键值.py
Taowa_win-1.0.1.dist-info/METADATA
Taowa_win-1.0.1.dist-info/WHEEL
Taowa_win-1.0.1.dist-info/top_level.txt
Taowa_win-1.0.1.dist-info/RECORD
